Workbook

Sheet Гайд интервью
A1: «Погнали!»: гайд глубинного интервью
A2: 12 интервью, сентябрь 2026, 35–50 минут
A4: Цель | B4: Понять, как люди планируют путешествия, ищут попутчиков и публикуют туристический контент; выявить скрытые потребности и стоп-факторы
A5: Аудитория | B5: Активные путешественники, ядро 35–55 лет; разные уровни опыта (новички, средние, опытные)
A6: Выборка | B6: 12 респондентов: 10 из ядра 35–55 лет, 2 за его пределами (29 и 33 года) для сравнения; 4 города-миллионника и Краснодар, Воронеж, Нижний Новгород, Самара
A7: Формат | B7: Глубинное интервью 35–50 минут в Zoom или по телефону, аудиозапись с согласия респондента
A8: Темы | B8: 1) Как люди планируют путешествия; 2) Поиск попутчиков: кто, где, зачем; 3) Публикация контента: мотивы, барьеры, площадки; 4) Бронирование и конкуренты
A10: № | B10: Этап CJM | C10: Вопрос
A11: 1 | B11: Зарождение идеи | C11: Расскажите про последнюю поездку: как появилась идея куда-то поехать?
A12: 2 | B12: Вдохновение | C12: Где вы искали идеи и вдохновение? Что смотрели, читали, у кого спрашивали?
A13: 3 | B13: Выбор направления | C13: Как выбирали направление? Что сравнивали и чему доверяли?
A14: 4 | B14: Попутчики | C14: Ездите ли вы с попутчиками? Искали ли кого-то специально: где и как?
A15: 5 | B15: Попутчики | C15: Что вас пугает или останавливает при поиске попутчика?
A16: 6 | B16: Бронирование | C16: Как бронировали жильё, билеты, экскурсии? Что было неудобно?
A17: 7 | B17: Поездка | C17: Что во время поездки шло не по плану или было сложным?
A18: 8 | B18: После поездки | C18: Публикуете ли вы что-то о поездках? Где и зачем?
A19: 9 | B19: После поездки | C19: Что мешает публиковать или разочаровывает в этом?
A20: 10 | B20: После поездки | C20: Что вы делаете после возвращения: контакты, отзывы, планы на следующую?
A21: 11 | B21: Весь путь | C21: Какой сервис идеально помог бы вам от идеи до поездки?

Sheet Респонденты
A1: Респонденты
A2: Список участников интервью
A4: ID | B4: Имя | C4: Возраст | D4: Город | E4: Профессия | F4: Семья | G4: Поездок в год | H4: Сегмент | I4: Формат путешествий | J4: Дата интервью | K4: Длительность, мин | L4: Формат связи
A5: R1 | B5: Елена К. | C5: 38 | D5: Москва | E5: Руководитель отдела маркетинга | F5: Замужем, сын 11 лет | G5: 5 | H5: Опытный | I5: Семейные поездки, выходные | J5: 15.09.2026 | K5: 45 | L5: Zoom
A6: R2 | B6: Андрей М. | C6: 42 | D6: Санкт-Петербург | E6: IT-директор | F6: Женат | G6: 6 | H6: Опытный | I6: Хайкинг, города, с друзьями | J6: 15.09.2026 | K6: 50 | L6: Zoom
A7: R3 | B7: Марина Л. | C7: 47 | D7: Казань | E7: Главный бухгалтер | F7: В разводе | G7: 2 | H7: Новичок | I7: Раньше только через турагентство | J7: 16.09.2026 | K7: 40 | L7: Телефон
A8: R4 | B8: Сергей В. | C8: 51 | D8: Екатеринбург | E8: Владелец автосервиса | F8: Женат | G8: 4 | H8: Опытный | I8: Автопутешествия | J8: 17.09.2026 | K8: 40 | L8: Телефон
A9: R5 | B9: Ольга Т. | C9: 44 | D9: Новосибирск | E9: Врач-терапевт | F9: Не замужем | G9: 3 | H9: Средний | I9: Море, отдых, хочет компанию | J9: 18.09.2026 | K9: 45 | L9: Zoom
A10: R6 | B10: Дмитрий Ф. | C10: 36 | D10: Москва | E10: Менеджер по продажам | F10: Женат | G10: 4 | H10: Средний | I10: Город + пляж, с женой и друзьями | J10: 19.09.2026 | K10: 35 | L10: Zoom
A11: R7 | B11: Татьяна Н. | C11: 55 | D11: Краснодар | E11: Учитель | F11: Замужем | G11: 3 | H11: Средний | I11: Экскурсионные поездки, групповые | J11: 21.09.2026 | K11: 40 | L11: Телефон
A12: R8 | B12: Алексей Р. | C12: 40 | D12: Нижний Новгород | E12: Инженер | F12: Женат | G12: 5 | H12: Опытный | I12: Походы, треккинг | J12: 22.09.2026 | K12: 50 | L12: Zoom
A13: R9 | B13: Наталья С. | C13: 49 | D13: Самара | E13: HR-директор | F13: В разводе | G13: 6 | H13: Опытный | I13: Соло-путешествия | J13: 23.09.2026 | K13: 45 | L13: Zoom
A14: R10 | B14: Игорь Б. | C14: 45 | D14: Москва | E14: Юрист | F14: Женат, двое детей | G14: 3 | H14: Средний | I14: Семейный отдых | J14: 24.09.2026 | K14: 35 | L14: Zoom
A15: R11 | B15: Юлия Г. | C15: 33 | D15: Казань | E15: Дизайнер | F15: Не замужем | G15: 7 | H15: Опытный | I15: Города, короткие поездки, блог | J15: 25.09.2026 | K15: 50 | L15: Zoom
A16: R12 | B16: Павел Д. | C16: 29 | D16: Воронеж | E16: Разработчик | F16: Не женат | G16: 1 | H16: Новичок | I16: Первая самостоятельная поездка | J16: 26.09.2026 | K16: 35 | L16: Телефон
A18: Всего респондентов | C18: =COUNTA(A5:A16) -> 12
A19: В ядре 35–55 лет | C19: =COUNTIFS(C5:C16,">=35",C5:C16,"<=55") -> 10
A20: Средний возраст | C20: =AVERAGE(C5:C16) -> 42.416667

Sheet Расшифровки
A1: Расшифровки интервью
A2: Ответы респондентов по вопросам гайда
A4: ID | B4: Респондент | C4: Вопрос № | D4: Этап CJM | E4: Вопрос | F4: Ответ
A5: R1 | B5: Елена К. | C5: 1 | D5: Зарождение идеи | E5: Расскажите про последнюю поездку: как появилась идея куда-то поехать? | F5: Поняла, что выгорела: до отпуска ещё три месяца, а я уже считаю дни. Сначала просто захотелось куда-то на выходные, потом мы с мужем решили сделать нормальную поездку на майские.
A6: R1 | B6: Елена К. | C6: 2 | D6: Вдохновение | E6: Где вы искали идеи и вдохновение? Что смотрели, читали, у кого спрашивали? | F6: Telegram-каналы про путешествия, пара блогеров на YouTube. Скидываю ссылки себе в «Избранное», а потом месяц не могу найти, что именно сохраняла.
A7: R1 | B7: Елена К. | C7: 3 | D7: Выбор направления | E7: Как выбирали направление? Что сравнивали и чему доверяли? | F7: Сравниваю по погоде, цене перелёта и отзывам. Отзывам на агрегаторах не верю, половина выглядит заказанной. Проверяю по фото от реальных людей на Яндекс Картах.
A8: R1 | B8: Елена К. | C8: 4 | D8: Попутчики | E8: Ездите ли вы с попутчиками? Искали ли кого-то специально: где и как? | F8: С мужем и сыном, попутчиков не искала. Один раз хотела позвать подругу, но у неё не сошлись даты, и мы отказались от этой идеи.
A9: R1 | B9: Елена К. | C9: 5 | D9: Попутчики | E9: Что вас пугает или останавливает при поиске попутчика? | F9: Для меня это не актуально: с семьёй ездить привычнее. Незнакомых в поездку я бы брать не стала.
A10: R1 | B10: Елена К. | C10: 6 | D10: Бронирование | E10: Как бронировали жильё, билеты, экскурсии? Что было неудобно? | F10: Ищу отель на агрегаторе, потом иду на сайт отеля и смотрю, дешевле ли там. Обычно дешевле или с завтраком. В итоге десять вкладок и таблица в Excel.
A11: R1 | B11: Елена К. | C11: 7 | D11: Поездка | E11: Что во время поездки шло не по плану или было сложным? | F11: Всё прошло по плану. Единственное: забыла, что записала про ресторан, и полчаса искала по чатам и заметкам.
A12: R1 | B12: Елена К. | C12: 8 | D12: После поездки | E12: Публикуете ли вы что-то о поездках? Где и зачем? | F12: Выкладываю в закрытый чат с друзьями в Telegram и иногда в ВК. Для себя и чтобы близкие видели, как мы отдохнули.
A13: R1 | B13: Елена К. | C13: 9 | D13: После поездки | E13: Что мешает публиковать или разочаровывает в этом? | F13: Мне не мешает, я и не жду лайков, это для своих. Просто лень разбирать 300 фото.
A14: R1 | B14: Елена К. | C14: 10 | D14: После поездки | E14: Что вы делаете после возвращения: контакты, отзывы, планы на следующую? | F14: Показываю друзьям, советую места. Отзывы пишу редко, только если очень понравилось или очень плохо. Следующую поездку начинаем планировать через месяц-два.
A15: R1 | B15: Елена К. | C15: 11 | D15: Весь путь | E15: Какой сервис идеально помог бы вам от идеи до поездки? | F15: Чтобы всё было в одном месте: идеи, сохранённые места, план, бронь. И чтобы советы были от нормальных людей, а не рекламные.
A16: R2 | B16: Андрей М. | C16: 1 | D16: Зарождение идеи | E16: Расскажите про последнюю поездку: как появилась идея куда-то поехать? | F16: Идея появилась в чате друзей: кто-то скинул фото с Кольского, и началось: давайте, когда, на сколько. Обычно всё решается за пару вечеров в Telegram.
... A136: R12 | B136: Павел Д. | C136: 11 | D136: Весь путь | E136: Какой сервис идеально помог бы вам от идеи до поездки? | F136: Чтобы можно было выбрать направление по моим датам и бюджету и сразу найти компанию: понятно и без хаоса.

Sheet Кодирование
A1: Кодирование ответов
A2: 1 = проблема или поведение подтверждено в интервью респондента, 0 = нет
A4: ID | B4: Респондент | C4: Сегмент | D4: Искал(а) попутчиков | E4: Публикует контент | F4: Бронирует напрямую после агрегатора | G4: P1 Нет единого канала поиска попутчиков: чаты и группы без структуры, объявления теряются | H4: P2 Страх незнакомцев: нет верификации, рейтинга и гарантий | I4: P3 Хаос источников вдохновения: десятки каналов, сохранённое не найти | J4: P4 Недоверие к отзывам и рекламному контенту | K4: P5 Разрозненное бронирование: агрегатор как каталог, сверка цен в десятках вкладок | L4: P6 Нет отклика на публикации: «пишешь в пустоту», нет смысла постить | M4: P7 Сложно согласовать даты, бюджет и темп поездки с попутчиком | N4: P8 План, заметки и места разбросаны по мессенджерам, Notes и таблицам | O4: P9 Нет локальных советов, гидов и активностей на месте | P4: P10 Контакты попутчиков и впечатления теряются после поездки
A5: R1 | B5: Елена К. | C5: Опытный | D5: 0 | E5: 1 | F5: 1 | G5: 0 | H5: 0 | I5: 1 | J5: 1 | K5: 1 | L5: 0 | M5: 0 | N5: 1 | O5: 0 | P5: 0
A6: R2 | B6: Андрей М. | C6: Опытный | D6: 1 | E6: 1 | F6: 1 | G6: 1 | H6: 0 | I6: 1 | J6: 1 | K6: 1 | L6: 0 | M6: 1 | N6: 1 | O6: 0 | P6: 1
A7: R3 | B7: Марина Л. | C7: Новичок | D7: 1 | E7: 0 | F7: 0 | G7: 1 | H7: 1 | I7: 0 | J7: 0 | K7: 0 | L7: 1 | M7: 0 | N7: 0 | O7: 1 | P7: 1
A8: R4 | B8: Сергей В. | C8: Опытный | D8: 1 | E8: 0 | F8: 1 | G8: 1 | H8: 1 | I8: 0 | J8: 1 | K8: 1 | L8: 0 | M8: 1 | N8: 0 | O8: 0 | P8: 1
A9: R5 | B9: Ольга Т. | C9: Средний | D9: 1 | E9: 0 | F9: 1 | G9: 1 | H9: 1 | I9: 1 | J9: 0 | K9: 0 | L9: 1 | M9: 1 | N9: 0 | O9: 1 | P9: 0
A10: R6 | B10: Дмитрий Ф. | C10: Средний | D10: 0 | E10: 1 | F10: 1 | G10: 0 | H10: 0 | I10: 1 | J10: 1 | K10: 1 | L10: 1 | M10: 0 | N10: 1 | O10: 1 | P10: 0
A11: R7 | B11: Татьяна Н. | C11: Средний | D11: 1 | E11: 1 | F11: 0 | G11: 1 | H11: 1 | I11: 0 | J11: 1 | K11: 0 | L11: 1 | M11: 0 | N11: 0 | O11: 1 | P11: 0
A12: R8 | B12: Алексей Р. | C12: Опытный | D12: 1 | E12: 1 | F12: 1 | G12: 1 | H12: 0 | I12: 1 | J12: 0 | K12: 1 | L12: 0 | M12: 1 | N12: 1 | O12: 0 | P12: 1
A13: R9 | B13: Наталья С. | C13: Опытный | D13: 0 | E13: 1 | F13: 1 | G13: 0 | H13: 1 | I13: 1 | J13: 1 | K13: 1 | L13: 1 | M13: 0 | N13: 1 | O13: 0 | P13: 1
A14: R10 | B14: Игорь Б. | C14: Средний | D14: 0 | E14: 0 | F14: 1 | G14: 0 | H14: 0 | I14: 1 | J14: 1 | K14: 1 | L14: 0 | M14: 0 | N14: 1 | O14: 1 | P14: 0
A15: R11 | B15: Юлия Г. | C15: Опытный | D15: 1 | E15: 1 | F15: 1 | G15: 1 | H15: 1 | I15: 1 | J15: 0 | K15: 1 | L15: 1 | M15: 1 | N15: 1 | O15: 0 | P15: 1
A16: R12 | B16: Павел Д. | C16: Новичок | D16: 1 | E16: 0 | F16: 0 | G16: 1 | H16: 0 | I16: 1 | J16: 0 | K16: 1 | L16: 1 | M16: 1 | N16: 0 | O16: 1 | P16: 0
B18: Всего «да» | D18: =SUM(D5:D16) -> 8 | E18: =SUM(E5:E16) -> 7 | F18: =SUM(F5:F16) -> 9 | G18: =SUM(G5:G16) -> 8 | H18: =SUM(H5:H16) -> 6 | I18: =SUM(I5:I16) -> 9 | J18: =SUM(J5:J16) -> 7 | K18: =SUM(K5:K16) -> 9 | ... P18: =SUM(P5:P16) -> 6
B19: Доля респондентов | D19: =D18/COUNTA($A$5:$A$16) -> 0.66666667 | E19: =E18/COUNTA($A$5:$A$16) -> 0.58333333 | F19: =F18/COUNTA($A$5:$A$16) -> 0.75 | G19: =G18/COUNTA($A$5:$A$16) -> 0.66666667 | H19: =H18/COUNTA($A$5:$A$16) -> 0.5 | I19: =I18/COUNTA($A$5:$A$16) -> 0.75 | J19: =J18/COUNTA($A$5:$A$16) -> 0.58333333 | K19: =K18/COUNTA($A$5:$A$16) -> 0.75 | ... P19: =P18/COUNTA($A$5:$A$16) -> 0.5

Sheet Проблемы
A1: Ключевые проблемы и инсайты
A2: Количество респондентов считается формулами из листа «Кодирование»
A4: Ранг | B4: Код | C4: Проблема | D4: Этап CJM | E4: Респондентов (из 12) | F4: Доля | G4: Приоритет | H4: Цитата | I4: Скрытая потребность (инсайт)
A5: =RANK(E5,$E$5:$E$14) -> 1 | B5: P3 | C5: Хаос источников вдохновения: десятки каналов, сохранённое не найти | D5: 2. Вдохновение | E5: =Кодирование!I18 -> 9 | F5: =Кодирование!I19 -> 0.75 | G5: =IF(F5>=0.75,"Критично",IF(F5>=0.58,"Высокий","Значимый")) -> Критично | H5: «Подписана на 30 каналов, не помню, где что видела» (R11) | I5: Хочу одно место для идей, а не 30 каналов
A6: =RANK(E6,$E$5:$E$14) -> 1 | B6: P5 | C6: Разрозненное бронирование: агрегатор как каталог, сверка цен в десятках вкладок | D6: 5. Бронирование | E6: =Кодирование!K18 -> 9 | F6: =Кодирование!K19 -> 0.75 | G6: =IF(F6>=0.75,"Критично",IF(F6>=0.58,"Высокий","Значимый")) -> Критично | H6: «Ищу отель на агрегаторе, потом иду на сайт отеля… В итоге десять вкладок и таблица в Excel» (R1) | I6: Платформе не лоялен: ищу выгоду; удержит сообщество
A7: =RANK(E7,$E$5:$E$14) -> 3 | B7: P1 | C7: Нет единого канала поиска попутчиков: чаты и группы без структуры, объявления теряются | D7: 4. Попутчики | E7: =Кодирование!G18 -> 8 | F7: =Кодирование!G19 -> 0.66666667 | G7: =IF(F7>=0.75,"Критично",IF(F7>=0.58,"Высокий","Значимый")) -> Высокий | H7: «Писал в Telegram-чаты, но там сотни объявлений без структуры, по датам не поискать» (R12) | I7: Хочу один проверенный канал, а не гадать, где искать
A8: =RANK(E8,$E$5:$E$14) -> 4 | B8: P4 | C8: Недоверие к отзывам и рекламному контенту | D8: 3. Выбор направления | E8: =Кодирование!J18 -> 7 | F8: =Кодирование!J19 -> 0.58333333 | G8: =IF(F8>=0.75,"Критично",IF(F8>=0.58,"Высокий","Значимый")) -> Высокий | H8: «Отзывы в интернете накручены, верю только отчётам тех, кто проехал» (R4) | I8: Доверяю людям «как я», а не рекламе
A9: =RANK(E9,$E$5:$E$14) -> 4 | B9: P6 | C9: Нет отклика на публикации: «пишешь в пустоту», нет смысла постить | D9: 7. После поездки | E9: =Кодирование!L18 -> 7 | F9: =Кодирование!L19 -> 0.58333333 | G9: =IF(F9>=0.75,"Критично",IF(F9>=0.58,"Высокий","Значимый")) -> Высокий | H9: «Охваты маленькие. Пишешь в пустоту, а хочется обратной связи» (R11) | I9: Хочу признания и отклика от тех, кому это интересно
A10: =RANK(E10,$E$5:$E$14) -> 4 | B10: P8 | C10: План, заметки и места разбросаны по мессенджерам, Notes и таблицам | D10: 3. Выбор направления | E10: =Кодирование!N18 -> 7 | F10: =Кодирование!N19 -> 0.58333333 | G10: =IF(F10>=0.75,"Критично",IF(F10>=0.58,"Высокий","Значимый")) -> Высокий | H10: «Заметки по маршруту были в трёх местах: в Notes, в чате и в таблице» (R2) | I10: Хочу, чтобы план был в одном месте и не терялся
A11: =RANK(E11,$E$5:$E$14) -> 7 | B11: P2 | C11: Страх незнакомцев: нет верификации, рейтинга и гарантий | D11: 4. Попутчики | E11: =Кодирование!H18 -> 6 | F11: =Кодирование!H19 -> 0.5 | G11: =IF(F11>=0.75,"Критично",IF(F11>=0.58,"Высокий","Значимый")) -> Значимый | H11: «Боюсь незнакомцев… нужно понимать, что человек реальный: документы, отзывы, общие знакомые» (R5) | I11: Хочу чувствовать себя в безопасности: нужна верификация
A12: =RANK(E12,$E$5:$E$14) -> 7 | B12: P7 | C12: Сложно согласовать даты, бюджет и темп поездки с попутчиком | D12: 4. Попутчики | E12: =Кодирование!M18 -> 6 | F12: =Кодирование!M19 -> 0.5 | G12: =IF(F12>=0.75,"Критично",IF(F12>=0.58,"Высокий","Значимый")) -> Значимый | H12: «Согласовать даты, бюджет и физподготовку — половина нервов» (R2) | I12: Хочу ехать с человеком «моего формата», а не договариваться с нуля
A13: =RANK(E13,$E$5:$E$14) -> 7 | B13: P9 | C13: Нет локальных советов, гидов и активностей на месте | D13: 6. Поездка | E13: =Кодирование!O18 -> 6 | F13: =Кодирование!O19 -> 0.5 | G13: =IF(F13>=0.75,"Критично",IF(F13>=0.58,"Высокий","Значимый")) -> Значимый | H13: «На месте не знал, что посмотреть рядом… хочется, чтобы кто-то местный посоветовал» (R6) | I13: Хочу «местного друга» на месте
A14: =RANK(E14,$E$5:$E$14) -> 7 | B14: P10 | C14: Контакты попутчиков и впечатления теряются после поездки | D14: 7. После поездки | E14: =Кодирование!P18 -> 6 | F14: =Кодирование!P19 -> 0.5 | G14: =IF(F14>=0.75,"Критично",IF(F14>=0.58,"Высокий","Значимый")) -> Значимый | H14: «Контакты растворяются в чатах. Хочу ездить с теми, с кем было хорошо, но через полгода не могу их найти» (R11) | I14: Хочу сохранить людей, с которыми было хорошо
A16: Порог приоритета: «Критично» — 75% и выше, «Высокий» — от 58%, «Значимый» — ниже.

Sheet Сводка
A1: Ключевые цифры исследования
A4: Показатель | B4: Респондентов | C4: Доля
A5: Искали попутчиков за последние 2 года | B5: =Кодирование!D18 -> 8 | C5: =Кодирование!D19 -> 0.66666667
A6: Публикуют туристический контент | B6: =Кодирование!E18 -> 7 | C6: =Кодирование!E19 -> 0.58333333
A7: Бронируют напрямую после поиска на агрегаторе | B7: =Кодирование!F18 -> 9 | C7: =Кодирование!F19 -> 0.75
A9: Из искавших попутчиков: не нашли удобного канала | B9: =Кодирование!G18 -> 8 | C9: =Кодирование!G18/Кодирование!D18 -> 1
A10: Из искавших попутчиков: страх незнакомцев | B10: =SUMPRODUCT(Кодирование!D5:D16,Кодирование!H5:H16) -> 5 | C10: =B10/Кодирование!D18 -> 0.625
A12: Каналы
A13: Канал | B13: Вдохновение | C13: Поиск попутчиков | D13: Публикации
A14: Telegram | B14: =COUNTIF(Каналы!C$5:C$16,"*Telegram*") -> 8 | C14: =COUNTIF(Каналы!D$5:D$16,"*Telegram*") -> 5 | D14: =COUNTIF(Каналы!E$5:E$16,"*Telegram*") -> 6
A15: ВК | B15: =COUNTIF(Каналы!C$5:C$16,"*ВК*") -> 4 | C15: =COUNTIF(Каналы!D$5:D$16,"*ВК*") -> 4 | D15: =COUNTIF(Каналы!E$5:E$16,"*ВК*") -> 5
A16: YouTube | B16: =COUNTIF(Каналы!C$5:C$16,"*YouTube*") -> 9 | C16: =COUNTIF(Каналы!D$5:D$16,"*YouTube*") -> 0 | D16: =COUNTIF(Каналы!E$5:E$16,"*YouTube*") -> 0
A17: Дзен | B17: =COUNTIF(Каналы!C$5:C$16,"*Дзен*") -> 3 | C17: =COUNTIF(Каналы!D$5:D$16,"*Дзен*") -> 0 | D17: =COUNTIF(Каналы!E$5:E$16,"*Дзен*") -> 0
A18: Одноклассники | B18: =COUNTIF(Каналы!C$5:C$16,"*Одноклассники*") -> 1 | C18: =COUNTIF(Каналы!D$5:D$16,"*Одноклассники*") -> 0 | D18: =COUNTIF(Каналы!E$5:E$16,"*Одноклассники*") -> 1
A19: Drive2 | B19: =COUNTIF(Каналы!C$5:C$16,"*Drive2*") -> 1 | C19: =COUNTIF(Каналы!D$5:D$16,"*Drive2*") -> 1 | D19: =COUNTIF(Каналы!E$5:E$16,"*Drive2*") -> 0
A20: Сетка | B20: =COUNTIF(Каналы!C$5:C$16,"*Сетка*") -> 0 | C20: =COUNTIF(Каналы!D$5:D$16,"*Сетка*") -> 1 | D20: =COUNTIF(Каналы!E$5:E$16,"*Сетка*") -> 0
A21: друзья | B21: =COUNTIF(Каналы!C$5:C$16,"*друзья*") -> 9 | C21: =COUNTIF(Каналы!D$5:D$16,"*друзья*") -> 7 | D21: =COUNTIF(Каналы!E$5:E$16,"*друзья*") -> 0
A22: Яндекс Карты | B22: =COUNTIF(Каналы!C$5:C$16,"*Яндекс Карты*") -> 0 | C22: =COUNTIF(Каналы!D$5:D$16,"*Яндекс Карты*") -> 0 | D22: =COUNTIF(Каналы!E$5:E$16,"*Яндекс Карты*") -> 3

Sheet Каналы
A1: Каналы и площадки по респондентам
A4: ID | B4: Респондент | C4: Где ищут вдохновение | D4: Где ищут попутчиков | E4: Где публикуют
A5: R1 | B5: Елена К. | C5: Telegram, YouTube, друзья | D5: — | E5: Telegram, ВК
A6: R2 | B6: Андрей М. | C6: Telegram, ВК, друзья, YouTube | D6: Telegram, ВК, друзья | E6: ВК, Telegram
A7: R3 | B7: Марина Л. | C7: ВК, друзья | D7: ВК, друзья | E7: —
A8: R4 | B8: Сергей В. | C8: Drive2, YouTube, друзья | D8: Drive2, друзья | E8: —
A9: R5 | B9: Ольга Т. | C9: Telegram, друзья | D9: Telegram, друзья | E9: —
A10: R6 | B10: Дмитрий Ф. | C10: Telegram, YouTube, Дзен | D10: — | E10: Telegram, ВК, Яндекс Карты
A11: R7 | B11: Татьяна Н. | C11: ВК, Одноклассники, друзья | D11: ВК, друзья | E11: ВК, Одноклассники
A12: R8 | B12: Алексей Р. | C12: Telegram, YouTube, друзья | D12: Telegram, друзья | E12: Telegram, Яндекс Карты
A13: R9 | B13: Наталья С. | C13: Telegram, YouTube, Дзен | D13: — | E13: Telegram, Яндекс Карты
A14: R10 | B14: Игорь Б. | C14: YouTube, Дзен, друзья | D14: — | E14: —
A15: R11 | B15: Юлия Г. | C15: Telegram, ВК, YouTube | D15: Telegram, ВК, Сетка | E15: Telegram, ВК
A16: R12 | B16: Павел Д. | C16: YouTube, Telegram, друзья | D16: Telegram, друзья | E16: —

Sheet CJM
A1: Customer Journey Map: путешественник и сервис «Погнали!»
A2: Этапы одинаковы для всех 12 респондентов
A4: Этап | B4: 1. Зарождение идеи | C4: 2. Вдохновение | D4: 3. Выбор направления | E4: 4. Поиск попутчиков | F4: 5. Бронирование | G4: 6. Поездка | H4: 7. После поездки
A5: Точки контакта | B5: Разговор с семьёй и друзьями, чужой пост, календарь отпусков | C5: Telegram-каналы, ВК, YouTube, Дзен, рассказы знакомых | D5: Отзывы, Яндекс Карты, отчёты людей, семейные обсуждения | E5: Telegram-чаты, ВК-группы, Drive2, друзья | F5: Агрегаторы, сайты отелей, РЖД, агентства | G5: Карты, чаты с группой, гиды, советы местных | H5: Telegram, ВК, Яндекс Карты, личные чаты
A6: Что делает? | B6: Накапливает усталость, выбирает окно в отпуске, обсуждает идею с близкими; идея часто приходит из чужого поста | C6: Листает каналы и соцсети, спрашивает знакомых, сохраняет ссылки в «Избранное» и заметки | D6: Сравнивает цену, погоду, логистику и отзывы, ищет отчёты людей, которые там были, ведёт таблицы | E6: Пишет в Telegram-чаты и ВК-группы, спрашивает знакомых, согласует даты, бюджет и темп (8 из 12 искали) | F6: Ищет на агрегаторе, проверяет цену на сайте отеля, бронирует напрямую; с попутчиками делит счета вручную | G6: Идёт по плану, ищет, что посмотреть и где поужинать, общается с группой, подстраивает маршрут | H6: Делится фото и отчётами (7 из 12), пишет отзывы на картах, сохраняет контакты, начинает думать о следующей поездке
A7: Что думает? | B7: «Накопилась усталость, надо куда-то выбраться, но куда — пока не знаю» | C7: «Уже не помню, где я это видел. Много рекламы под видом личного опыта» | D7: «Отзывам не верю, лучше спрошу человека, который там был, но найти его — отдельная задача» | E7: «Надеюсь, хоть кто-то откликнется. Вдруг человек окажется странным или пропадёт перед вылетом?» | F7: «Посмотрю в каталоге, а закажу на сайте отеля, там дешевле. Десять вкладок, уже путаюсь» | G7: «Хорошо бы, чтобы кто-то местный подсказал, что тут ещё интересного и безопасного» | H7: «Выложил, два лайка — и всё. Жалко, что контакты потерялись»
A8: Что чувствует? | B8: Усталость, предвкушение, лёгкая тревога «не упустить даты» | C8: Интерес, затем перегруз и раздражение от рекламы | D8: Сомнение, усталость от сравнения вариантов | E8: Тревога, неуверенность, страх обмана, надежда | F8: Раздражение, желание контроля, нервозность при оплате | G8: Радость, свобода; иногда растерянность и одиночество | H8: Гордость, затем разочарование от отсутствия отклика; ностальгия
A9: Боли | B9: Идея рождается из чужих историй, а не из поиска; страх упустить удачные даты и цены | C9: Хаос источников (9 из 12); недоверие к рекламному контенту (7 из 12) | D9: Недоверие к отзывам (7 из 12); план и заметки разбросаны по мессенджерам (7 из 12) | E9: Нет единого канала (8 из 12); страх незнакомцев (6 из 12); сложно согласовать даты, бюджет, темп (6 из 12) | F9: Разрозненное бронирование и сверка цен (9 из 12); агрегаторы используют как каталог | G9: Нет локальных советов, гидов и активностей на месте (6 из 12) | H9: Нет отклика на публикации (7 из 12); контакты попутчиков теряются (6 из 12)
A10: Возможности для «Погнали!» | B10: Идеи под даты и бюджет («куда поехать на 4 дня в ноябре»); напоминания об удачных окнах отпуска | C10: Лента идей из реального опыта путешественников (UGC), подборки без рекламы, кнопка «сохранить в мой план» | D10: Маршруты от людей, которые там были, вопрос-ответ «спроси бывавших», единый план поездки | E10: Объявления по направлению и датам, верификация и рейтинг, подбор по стилю и бюджету, чат до поездки | F10: Совместное бронирование и деление счёта в группе, прямые предложения отелей, план и бронь в одном месте | G10: Режим «рядом со мной»: активности, гиды и люди на месте; план офлайн | H10: Публикации для профильной аудитории, отзывы → рейтинг, «поехать снова с теми же людьми», карта моих поездок
A11: Инсайт | B11: Желание рождается до поиска: сервис должен поймать момент «хочу уехать», а не ждать запроса | C11: Доверяют «таким же, как я», а не блогерам: нужен живой опыт вместо рекламы | D11: Человеку нужен не выбор побольше, а уверенность, что решение правильное | E11: Хочу один проверенный канал и чувствовать себя в безопасности | F11: Лояльности к платформам нет; удерживает сообщество, а не скидка | G11: В поездке нужен «местный друг»: быстрый живой совет и компания | H11: Хочу признания и обратной связи от тех, кому это интересно
A12: Эмоции (1 — негатив, 5 — позитив) | B12: 4 | C12: 3 | D12: 3 | E12: 2 | F12: 3 | G12: 5 | H12: 3
